darkchess/__init__.py
darkchess/src/__init__.py
darkchess/src/bishop.py
darkchess/src/board.py
darkchess/src/darkboard.py
darkchess/src/dummy_piece.py
darkchess/src/gamengine.py
darkchess/src/king.py
darkchess/src/knight.py
darkchess/src/pawn.py
darkchess/src/piece.py
darkchess/src/queen.py
darkchess/src/rook.py
darkchess/src/utils.py
darkchess/tests/__init__.py
darkchess/tests/test_bishop/__init__.py
darkchess/tests/test_bishop/test_bishop.py
darkchess/tests/test_enpasse/__init__.py
darkchess/tests/test_enpasse/test_enpasse.py
darkchess/tests/test_knight/__init__.py
darkchess/tests/test_knight/test_knight.py
darkchess/tests/test_normalgame/__init__.py
darkchess/tests/test_normalgame/test_normalgame.py
darkchess/tests/test_pawn/__init__.py
darkchess/tests/test_pawn/test_pawn.py
darkchess/tests/test_queen/__init__.py
darkchess/tests/test_queen/test_queen.py
darkchess/tests/test_rook/__init__.py
darkchess/tests/test_rook/test_rook.py
darkchess/tests/test_stalemate/__init__.py
darkchess/tests/test_stalemate/test_stalemate.py
darkchess-0.0.1.dist-info/LICENSE
darkchess-0.0.1.dist-info/METADATA
darkchess-0.0.1.dist-info/WHEEL
darkchess-0.0.1.dist-info/top_level.txt
darkchess-0.0.1.dist-info/RECORD
