Metadata-Version: 2.1
Name: darkchess
Version: 0.0.1
Summary: incomplete information chess
Home-page: https://github.com/vishalsubbiah/darkchess
Author: Vishal Subbiah
Author-email: subbiahvishal@gmail.com
License: UNKNOWN
Platform: UNKNOWN
Classifier: Programming Language :: Python :: 3
Classifier: Intended Audience :: Developers
Classifier: Development Status :: 2 - Pre-Alpha
Classifier: License :: OSI Approved :: Apache Software License
Classifier: Operating System :: OS Independent
Requires-Dist: numpy
Requires-Dist: sty
Requires-Dist: mock
Requires-Dist: pytest
